{
  "episodes": [
    {
      "id": "E_S_001",
      "theme": "比較から自由になる技術",
      "scene": "上司が「○○さんはもっと早くやってたのに」と言った3秒後、その目が泳いだ。その週、自分のプロジェクトが遅れていた。",
      "last_used_date": "2026-06-09"
    },
    {
      "id": "E_S_002",
      "theme": "比較から自由になる技術",
      "scene": "「あなたは○○ちゃんと違って」と親に言われた夜、布団の中で何時間も泣いた。翌朝、何も言えなかった。",
      "last_used_date": "2026-06-09"
    },
    {
      "id": "E_S_003",
      "theme": "比較から自由になる技術",
      "scene": "職場で比べてくる人が一番饒舌になるのは、決まって自分が追い詰められている月末だった。",
      "last_used_date": "2026-06-09"
    },
    {
      "id": "E_S_004",
      "theme": "比較から自由になる技術",
      "scene": "ある朝突然、「この人の物差しは私のサイズに作られていない」と腹の底でわかって、返事をしなくなった。",
      "last_used_date": "2026-06-09"
    },
    {
      "id": "E_S_005",
      "theme": "比較から自由になる技術",
      "scene": "「あなたは○○さんと違って」という言葉に何時間も傷ついた後、その言葉の主語が実は相手自身だったと気づいた夜。",
      "last_used_date": "2026-06-09"
    },
    {
      "id": "E_S_006",
      "theme": "本音が言えない関係の構造",
      "scene": "「重いと思われたら」と0.3秒で計算して、また本音を飲み込んだ帰り道。",
      "last_used_date": "2026-06-10"
    },
    {
      "id": "E_S_007",
      "theme": "本音が言えない関係の構造",
      "scene": "友人に「実は最近しんどくて」と言いかけて、「いや、重いか」と思った瞬間に「大丈夫！」に変えた会話。",
      "last_used_date": "2026-06-10"
    },
    {
      "id": "E_S_008",
      "theme": "本音が言えない関係の構造",
      "scene": "何度言っても変わらなかったので「言うのをやめた」という決断が、静かに関係を格下げした経緯。",
      "last_used_date": "2026-06-10"
    },
    {
      "id": "E_S_009",
      "theme": "本音が言えない関係の構造",
      "scene": "2時間の飲み会で「そうですよね」を繰り返した夜、帰り道の電車で一言も言葉が出てこなかった。",
      "last_used_date": "2026-06-10"
    },
    {
      "id": "E_S_010",
      "theme": "本音が言えない関係の構造",
      "scene": "何年も「仲がいい」と思っていた人に、一度も本音を言ったことがなかったと気づいた瞬間。",
      "last_used_date": "2026-06-10"
    },
    {
      "id": "E_S_011",
      "theme": "わかってくれないの正体",
      "scene": "「なんでわかってくれないの」と言いかけて「そもそも言葉にしていたか？」と問い直した瞬間。",
      "last_used_date": "2026-06-11"
    },
    {
      "id": "E_S_012",
      "theme": "わかってくれないの正体",
      "scene": "「なんかモヤっとした」を言語化できないまま「察してほしい」と思い続けた3日間。",
      "last_used_date": "2026-06-11"
    },
    {
      "id": "E_S_013",
      "theme": "わかってくれないの正体",
      "scene": "「言わなくてもわかってくれると思ってた」とパートナーに言われ、「伝えた」は「ほのめかし」だったと気づいた夜。",
      "last_used_date": "2026-06-11"
    },
    {
      "id": "E_S_014",
      "theme": "わかってくれないの正体",
      "scene": "「わかってくれない」が毎回同じ相手との間で繰り返されるとき、相手の「限界値」だと気づいた転換点。",
      "last_used_date": "2026-06-11"
    },
    {
      "id": "E_S_015",
      "theme": "わかってくれないの正体",
      "scene": "察する能力は愛情の大きさではなく「一緒にいた経験の共有量」だと腹落ちした日。",
      "last_used_date": "2026-06-11"
    },
    {
      "id": "E_S_016",
      "theme": "怒りの正体",
      "scene": "「なんでそんなことするの」と言った30分後に「本当は怖かっただけかも」と気づいた夜。",
      "last_used_date": "2026-06-12"
    },
    {
      "id": "E_S_017",
      "theme": "怒りの正体",
      "scene": "怒鳴った後、静かになった部屋で「私、傷ついてたんだ」と初めて気づいた瞬間。",
      "last_used_date": "2026-06-12"
    },
    {
      "id": "E_S_018",
      "theme": "怒りの正体",
      "scene": "「私も悪かったかもしれないけど、相手の方がもっと悪い」という計算で怒りを正当化した経験。",
      "last_used_date": "2026-06-12"
    },
    {
      "id": "E_S_019",
      "theme": "怒りの正体",
      "scene": "怒鳴り続ける人の話をひたすら聞いていたら、30分後に泣き出した。怒りの下に悲しみがあった。",
      "last_used_date": "2026-06-12"
    },
    {
      "id": "E_S_020",
      "theme": "怒りの正体",
      "scene": "怒っていた当時の自分が「傷ついた」と言えなかった理由が、後になってわかった瞬間。",
      "last_used_date": "2026-06-12"
    },
    {
      "id": "E_S_021",
      "theme": "嫉妬の使い方",
      "scene": "友人の昇進報告の投稿を見た瞬間、0.3秒で「いいな」という苦い感覚が来た。",
      "last_used_date": "2026-06-13"
    },
    {
      "id": "E_S_022",
      "theme": "嫉妬の使い方",
      "scene": "嫉妬した感情を封印しようとして、3日後に「どうせあの人は運がいいだけ」という言葉が浮かんできた。",
      "last_used_date": "2026-06-13"
    },
    {
      "id": "E_S_023",
      "theme": "嫉妬の使い方",
      "scene": "「どうせあの人は恵まれてるだけ」の後で「何が羨ましかったのか」を正直に書き出したら「行動力」だった。",
      "last_used_date": "2026-06-13"
    },
    {
      "id": "E_S_024",
      "theme": "嫉妬の使い方",
      "scene": "嫉妬した後「私なんて…」が始まり、その夜2時間スマホを触り続けた。",
      "last_used_date": "2026-06-13"
    },
    {
      "id": "E_S_025",
      "theme": "嫉妬の使い方",
      "scene": "「羨ましい→何が羨ましいのか」を書き出したら、次の行動が見えてきた。",
      "last_used_date": "2026-06-13"
    },
    {
      "id": "E_S_026",
      "theme": "惰性と安定の温度差",
      "scene": "「特に不満はない、でも特に喜びもない」——関係の温度をそう表現したとき、惰性と安定の違いが見えた。",
      "last_used_date": "2026-06-14"
    },
    {
      "id": "E_S_027",
      "theme": "惰性と安定の温度差",
      "scene": "「この人のこと、どう思ってるんだろう」とふと思って答えが出なかった夜、「ありがとう」を最後に言ったのがいつか思い出せなかった。",
      "last_used_date": "2026-06-14"
    },
    {
      "id": "E_S_028",
      "theme": "惰性と安定の温度差",
      "scene": "「今の関係を変えるより、このままの方が安全」と思い続けて3年が経っていた。",
      "last_used_date": "2026-06-14"
    },
    {
      "id": "E_S_029",
      "theme": "惰性と安定の温度差",
      "scene": "「今日もこの人と話したい」と思う日と「まあいっか」と思う日の割合が、1年で逆転していた。",
      "last_used_date": "2026-06-14"
    },
    {
      "id": "E_S_030",
      "theme": "惰性と安定の温度差",
      "scene": "「このままでいいのかな」という問いを持ちながら何もしないでいたら、気づいたら「どちらでもいい」になっていた。",
      "last_used_date": "2026-06-14"
    },
    {
      "id": "E_S_031",
      "theme": "自分を大切にする技術",
      "scene": "「自分を犠牲にするほど愛される」と信じて動き続けた結果、返ってきたのは感謝ではなく「当たり前」だった。",
      "last_used_date": "2026-06-15"
    },
    {
      "id": "E_S_032",
      "theme": "自分を大切にする技術",
      "scene": "「大丈夫」じゃないのに「大丈夫」と言い続けた3ヶ月後、本当に大丈夫じゃなくなった。",
      "last_used_date": "2026-06-15"
    },
    {
      "id": "E_S_033",
      "theme": "自分を大切にする技術",
      "scene": "断れる人を見て「いいな」と思ったとき、「私もそうしていいんだ」という気づきへの手前にいると気づいた。",
      "last_used_date": "2026-06-15"
    },
    {
      "id": "E_S_034",
      "theme": "自分を大切にする技術",
      "scene": "「自分のために動く＝わがまま」という方程式を長年信じていたことに気づいた日。",
      "last_used_date": "2026-06-15"
    },
    {
      "id": "E_S_035",
      "theme": "自分を大切にする技術",
      "scene": "「わがまま」と「自己尊重」は全然違う——そこを分けて考え始めた日から、断り方が変わった。",
      "last_used_date": "2026-06-15"
    }
  ]
}
