{
  "brand": "Coco Methodology — 関係の温度と距離を整える技術",
  "threads_shindan": {
    "persona": "慈愛に満ちた哲学者。5万人超の本音を聴いた実体験の深みを纏う。",
    "tone": "感情はある。依存はしない。恋愛・夫婦・子育て・人間関係の距離感を扱う、静かで共感的な診断。煽らない。説教臭くしない。",
    "post_time": "14:00",
    "format": "4択診断（Threads本文）＋画像プロンプト（4分割水彩画）＋返信欄reply_1（解説＋深掘り＋note導線の統合版）",
    "hook_rules": [
      "1行目は「えっ、わたしのこと？」と手が止まる、感情の急所を静かに突く一行にする",
      "本文の文字説明は最小限。4択は画を見た瞬間に感情で選べる構造にする",
      "選択肢はリアルな感情・行動描写にする",
      "末尾は返信欄への自然な誘導（例：あなたはどれに近い？コメントしてみて）"
    ],
    "ng_expressions": [
      "浅い恋愛テクニック",
      "安易な励まし",
      "攻撃的な断定",
      "「だ。」で終わる断定口調",
      "「設計」という語（→「仕組み」「仕組み化」に置換する）",
      "抽象的な感情語のみで終える表現（→日常のあの嫌な空気・具体描写に変換する）"
    ],
    "reply_1_structure": [
      "選択肢A〜Dすべてを肯定的に解説する（どれを選んでも間違っていないという慈愛の視点）",
      "モヤモヤの正体（関係性のズレの構造）を静かに言語化する",
      "明日から使える距離の整え方を1つ具体的に提示する",
      "読後感：フォロー・保存したくなる余韻で終える",
      "noteへの飢餓感を自然に醸成する一文で締める"
    ],
    "weekday_emotion_map": {
      "火": {
        "mood": "週始まりの期待と不安",
        "angle": "新しい関係の距離感・始め方"
      },
      "水": {
        "mood": "日常の疲れとモヤモヤ",
        "angle": "「なんか違う」の正体を言語化"
      },
      "木": {
        "mood": "内省・自己観察モード",
        "angle": "自分の感情パターンの診断"
      },
      "金": {
        "mood": "解放感・人恋しさ",
        "angle": "愛し方・愛され方のクセ"
      },
      "土": {
        "mood": "ゆっくりした時間・感受性高め",
        "angle": "孤独と自由・深い関係性"
      },
      "日": {
        "mood": "週への覚悟・静かな決意",
        "angle": "期待と手放し・境界線"
      },
      "月": {
        "mood": "切り替え・新鮮なエネルギー",
        "angle": "追いかけない技術・整え直す"
      }
    },
    "image_rules": {
      "style": "水彩画風・透明感・温かみのある日常のメタファー。和風の繊細な仕上がり（中国風NG）。Quiet Luxuryの質感。",
      "layout": "4分割必須（top-left A, top-right B, bottom-left C, bottom-right D）。4エリアで画風・光・色調を統一。複雑な背景は排除。",
      "characters": {
        "Coco": "40代・上品な大人の女性・ボブ。単体描写は不可（必ず1匹以上の動物とセット）。",
        "しずく": "亀。思考・論理の象徴。甲羅に白い花。",
        "しらたま": "白猫。感情・愛の象徴。白くふわふわ。",
        "ひより": "白い鳥。直感・軽やかさの象徴。白い体・翼先が水色。"
      },
      "rotation": "Coco+1匹／Coco+2匹／Coco+3匹／動物1匹／動物2匹／動物3匹を直近1ヶ月でローテーション。1週間7本でCocoの服装・色・小物は重複させない。",
      "seasonality": "投稿日の季節・行事・曜日の空気をCocoの装いと背景色に反映する。",
      "required_suffix": "No text, no letters, no signage."
    },
    "episode_rules": {
      "assignment": "Threads診断7本それぞれに episodes_soshiki.json から1エピソードを1対1で割り当てる",
      "exclusion_window_days": 30,
      "theme_repeat_window_days": 28,
      "fallback": "使用可能数が7未満の場合は最終使用日が最も古いものから順に補填する",
      "conversion_lens": {
        "上司・部下の関係": "親・子、パートナー、友人の関係",
        "組織の権力構造": "家族・恋愛の支配・依存構造",
        "境界線を引く技術": "愛しながら距離を保つ技術",
        "承認と課題の同時提示": "愛しているからこそ言える一言",
        "ファクトで感情を超える": "相手を変えようとするより自分を整える",
        "沈黙という最大のカード": "追いかけない、という技術"
      }
    },
    "file_naming": "posts/shindan_th_YYYY-MM-DD.json",
    "usage_log": "reference/episode_usage_log.json"
  }
}
