{
  "week": "2026-05-10_2026-05-16",
  "theme": "LINEスタンプ「きょうも、そのままで ③」宣伝週",
  "stamp_series": "きょうも、そのままで ③",
  "posts": [
    {
      "date": "2026-05-10",
      "platform": "Threads",
      "time": "07:00",
      "character": "🕊ひより",
      "purpose": "認知獲得",
      "content": "「おはよう」が言えなくなった人に、送ってほしいスタンプができました。\n\nきょうも、そのままで ③ — 発売中",
      "quote": "💍 言葉が出ない朝のための一枚"
    },
    {
      "date": "2026-05-10",
      "platform": "Threads",
      "time": "10:00",
      "character": "🐢しずく",
      "purpose": "共感獲得",
      "content": "梅雨入り前に、届け方を変えてみませんか。\n\n長文より、一枚のスタンプの方がちゃんと届くことがある。",
      "quote": "💍 届け方が、関係の温度を決める"
    },
    {
      "date": "2026-05-10",
      "platform": "Threads",
      "time": "14:00",
      "character": "🐈‍⬛しらたま",
      "purpose": "購買促進",
      "content": "「うまく言えない」を、かわいく解決するスタンプ。\n\nしらたまが代わりに言います。",
      "quote": "💍 言葉の代わりを、可愛く届ける"
    },
    {
      "date": "2026-05-10",
      "platform": "Threads",
      "time": "19:00",
      "character": "🕊ひより",
      "purpose": "共感獲得",
      "content": "今日も頑張ったね、って言いたいのに\nLINEを開けなかった夜のために作りました。",
      "quote": "💍 開けなかった夜の、代わりに"
    },
    {
      "date": "2026-05-11",
      "platform": "Threads",
      "time": "07:00",
      "character": "🐢しずく",
      "purpose": "共感獲得",
      "content": "月曜の朝、「また今週もよろしく」を\nコレで送ったら既読スルーされなかった。\n\nスタンプって、ちゃんと温度がある。",
      "quote": "💍 月曜の温度を、スタンプで上げる"
    },
    {
      "date": "2026-05-11",
      "platform": "Threads",
      "time": "10:00",
      "character": "🐈‍⬛しらたま",
      "purpose": "認知獲得",
      "content": "距離を縮めたいのに、送る言葉がわからないとき。\n\n答えはだいたい、この24枚の中にあります。",
      "quote": "💍 迷う前に、開いてほしい24枚"
    },
    {
      "date": "2026-05-11",
      "platform": "Threads",
      "time": "14:00",
      "character": "🕊ひより",
      "purpose": "共感獲得",
      "content": "「でも」が言えない関係に、\n代わりに送れるスタンプがある。\n\n言葉より先に、気持ちを届けよう。",
      "quote": "💍 言えない「でも」の、代わりに"
    },
    {
      "date": "2026-05-11",
      "platform": "Threads",
      "time": "19:00",
      "character": "🐢しずく",
      "purpose": "共感獲得",
      "content": "「ごめん」より「気をつけてね」で\n締めくくれる関係でいたい。\n\nそんなスタンプを、ひよりが持っています。",
      "quote": "💍 謝罪より、気遣いの温度を"
    },
    {
      "date": "2026-05-12",
      "platform": "Threads",
      "time": "07:00",
      "character": "🐈‍⬛しらたま",
      "purpose": "購買促進",
      "content": "職場の人に送りやすくて、でもちょっと温かい。\n\nそのちょうど真ん中のスタンプ、やっと作れました。",
      "quote": "💍 職場に使える、でも冷たくない"
    },
    {
      "date": "2026-05-12",
      "platform": "Threads",
      "time": "10:00",
      "character": "🕊ひより",
      "purpose": "共感獲得",
      "content": "「ご無沙汰しております」が\n水彩イラストになったら、こんなに可愛かった。\n\nひよりが手紙を届けてくれます。",
      "quote": "💍 ビジネス敬語を、やわらかく"
    },
    {
      "date": "2026-05-12",
      "platform": "Threads",
      "time": "14:00",
      "character": "🐢しずく",
      "purpose": "共感獲得",
      "content": "じめじめした今週も、\n一枚のスタンプで気持ちが整えられますように。\n\n「少しずつでいい」— しずくより",
      "quote": "💍 梅雨の重さを、しずくが受け取る"
    },
    {
      "date": "2026-05-12",
      "platform": "Threads",
      "time": "19:00",
      "character": "🐈‍⬛しらたま",
      "purpose": "共感獲得",
      "content": "言い過ぎても後悔、引いても後悔する。\n\nそのちょうど真ん中を\nCocoとしらたまが狙いました。",
      "quote": "💍 ちょうどいい距離を、スタンプで"
    },
    {
      "date": "2026-05-13",
      "platform": "Threads",
      "time": "07:00",
      "character": "🕊ひより",
      "purpose": "購買促進",
      "content": "送る言葉に迷ったとき、\n答えはだいたいこの24枚の中にある。\n\n一度試すと、戻れなくなります。",
      "quote": "💍 迷いをなくす、24枚の設計"
    },
    {
      "date": "2026-05-13",
      "platform": "Threads",
      "time": "10:00",
      "character": "🐢しずく",
      "purpose": "共感獲得",
      "content": "「少しずつでいい」を\n今すぐ送りたい人が、きっといる気がして作りました。\n\nしずくが雨の中を歩いています。",
      "quote": "💍 その人の背中に、そっと届けて"
    },
    {
      "date": "2026-05-13",
      "platform": "Threads",
      "time": "14:00",
      "character": "🐈‍⬛しらたま",
      "purpose": "共感獲得",
      "content": "週の半ば、「ふんばれ」じゃなく\n「そのままでいいよ」と言いたい水曜日。\n\nしらたまが、代わりに言います。",
      "quote": "💍 ふんばれより、そのままでいいよ"
    },
    {
      "date": "2026-05-13",
      "platform": "Threads",
      "time": "19:00",
      "character": "🕊ひより",
      "purpose": "共感獲得",
      "content": "今日失敗した人へ。\n\n「失敗のない人、会ったことないよ」\n— しらたまより",
      "quote": "💍 夜の失敗に、しらたまが寄り添う"
    },
    {
      "date": "2026-05-14",
      "platform": "Threads",
      "time": "07:00",
      "character": "🐢しずく",
      "purpose": "共感獲得",
      "content": "「またいつか」じゃなく、今日送ってほしい。\n\n温度は、今が一番伝わります。",
      "quote": "💍 温度は今日が、一番高い"
    },
    {
      "date": "2026-05-14",
      "platform": "Threads",
      "time": "10:00",
      "character": "🐈‍⬛しらたま",
      "purpose": "購買促進",
      "content": "大人になると言いにくくなる「大好き」。\n\nスタンプなら、ちゃんと届きます。\nCocoとしらたまが一緒に言います。",
      "quote": "💍 大人の「大好き」を、一枚で"
    },
    {
      "date": "2026-05-14",
      "platform": "Threads",
      "time": "14:00",
      "character": "🕊ひより",
      "purpose": "共感獲得",
      "content": "雨の日に送るだけで、\nちょっと相手の気持ちが上がるスタンプがある。\n\n梅雨の日の、ひとつの使い方。",
      "quote": "💍 梅雨の日こそ、スタンプを開いて"
    },
    {
      "date": "2026-05-14",
      "platform": "Threads",
      "time": "19:00",
      "character": "🐢しずく",
      "purpose": "共感獲得",
      "content": "「お疲れ様」より刺さる言葉を、\nしずくが知っています。\n\n「一歩成長だね」— 今日の君へ。",
      "quote": "💍 お疲れ様より深い、ひとこと"
    },
    {
      "date": "2026-05-15",
      "platform": "Threads",
      "time": "07:00",
      "character": "🐈‍⬛しらたま",
      "purpose": "購買促進",
      "content": "金曜日。\n今週、何も言えなかった人へ送る最後のチャンス。\n\nしらたまに言わせてください。",
      "quote": "💍 金曜夜、言えなかった言葉を今"
    },
    {
      "date": "2026-05-15",
      "platform": "Threads",
      "time": "10:00",
      "character": "🕊ひより",
      "purpose": "認知獲得",
      "content": "上品なのに温かい。\n\nそんなスタンプを作りたくて、\nCocoが生まれました。",
      "quote": "💍 品と温もりは、両立できる"
    },
    {
      "date": "2026-05-15",
      "platform": "Threads",
      "time": "14:00",
      "character": "🐢しずく",
      "purpose": "共感獲得",
      "content": "関係の温度を整えるのは、\n長文じゃなくて一枚のスタンプで十分だった。\n\nそれに気づいてから、LINEが楽になりました。",
      "quote": "💍 整えるのに、長文はいらない"
    },
    {
      "date": "2026-05-15",
      "platform": "Threads",
      "time": "19:00",
      "character": "🐈‍⬛しらたま",
      "purpose": "購買促進",
      "content": "週末前に、気になってる人のLINEを開けてみて。\n\n「楽しみ〜」って、しらたまが言います。",
      "quote": "💍 週末の予感を、しらたまと一緒に"
    },
    {
      "date": "2026-05-16",
      "platform": "Threads",
      "time": "07:00",
      "character": "🕊ひより",
      "purpose": "共感獲得",
      "content": "梅雨の土曜日も、\n紫陽花みたいに静かに輝いていてほしい。\n\nCocoとひよりより。",
      "quote": "💍 梅雨も、静かに輝いていい"
    },
    {
      "date": "2026-05-16",
      "platform": "Threads",
      "time": "10:00",
      "character": "🐢しずく",
      "purpose": "購買促進",
      "content": "「買ってよかった」じゃなく\n「なんで今まで持ってなかったの」と\n自分に言いたくなるスタンプです。",
      "quote": "💍 持っていなかった自分が、惜しい"
    },
    {
      "date": "2026-05-16",
      "platform": "Threads",
      "time": "14:00",
      "character": "🐈‍⬛しらたま",
      "purpose": "認知獲得",
      "content": "しらたま・しずく・ひよりと一緒に、\n言いたかった言葉を届けよう。\n\n「きょうも、そのままで ③」発売中。",
      "quote": "💍 言いたかった言葉を、三匹と一緒に"
    },
    {
      "date": "2026-05-16",
      "platform": "Threads",
      "time": "19:00",
      "character": "🕊ひより",
      "purpose": "共感獲得",
      "content": "今週もお疲れ様でした。\n\n次の月曜から、このスタンプが味方になります。\nきょうも、そのままで。",
      "quote": "💍 月曜の朝の、小さな味方"
    }
  ]
}
